{"Title":"Everything Everywhere All at Once","Year":"2022","Rated":"R","Released":"25 Mar 2022","Runtime":"139 min","Genre":"Action, Adventure, Comedy","Director":"Dan Kwan, Daniel Scheinert","Writer":"Dan Kwan, Daniel Scheinert","Actors":"Michelle Yeoh, Stephanie Hsu, Ke Huy Quan","Plot":"An aging Chinese immigrant is swept up in an insane adventure, where she alone can save the world by exploring other universes connecting with the lives she could have led.","Language":"English, Mandarin, Cantonese","Country":"United States","Awards":"1 win","Poster":"https://m.media-amazon.com/images/M/MV5BYTdiOTIyZTQtNmQ1OS00NjZlLWIyMTgtYzk5Y2M3ZDVmMDk1XkEyXkFqcGdeQXVyMTAzMDg4NzU0._V1_SX300.jpg","Ratings":[{"Source":"Internet Movie Database","Value":"8.8/10"},{"Source":"Rotten Tomatoes","Value":"97%"},{"Source":"Metacritic","Value":"81/100"}],"Metascore":"81","imdbRating":"8.8","imdbVotes":"38,557","imdbID":"tt6710474","Type":"movie","BoxOffice":"$43,307,007","Response":"True"}